{
	"credit": "Asc4Yin",
	"ambientocclusion": false,
	"textures": {
		"particle": "generic/chains",
		"bars": "generic/chains"
	},
	"elements": [
		{
			"from": [7, 0, 7],
			"to": [9, 16, 9],
			"rotation": {"angle": 0, "axis": "y", "origin": [8, 8, 8]},
			"faces": {
				"north": {"uv": [3, 0, 5, 16], "texture": "#bars"},
				"east": {"uv": [3, 0, 5, 16], "texture": "#bars"},
				"south": {"uv": [3, 0, 5, 16], "texture": "#bars"},
				"west": {"uv": [3, 0, 5, 16], "texture": "#bars"},
				"up": {"uv": [7, 3, 9, 5], "texture": "#bars"},
				"down": {"uv": [7, 11, 9, 13], "texture": "#bars"}
			}
		}
	],
	"display": {}
}